{
    "name": "Custom Orange Theme",
    "description": "A custom Discord theme with an orange tone.",
    "authors": [
        {
            "name": "Your_Name",
            "id": "Your_Discord_ID"
        }
    ],
    "semanticColors": {
        "HEADER_PRIMARY": "#ff5722",
        "HEADER_SECONDARY": "#ff9800",
        "TEXT_NORMAL": "#ffab40",
        "TEXT_MUTED": "#ffc400",
        "TEXT_LINK": "#ff6f00",
        "INTERACTIVE_NORMAL": "#ff8f00",
        "INTERACTIVE_HOVER": "#ef6c00",
        "INTERACTIVE_ACTIVE": "#d84315",
        "INTERACTIVE_MUTED": "#ffcc80",
        "BACKGROUND_PRIMARY": "#bf360c",
        "BACKGROUND_SECONDARY": "#ff5722",
        "BACKGROUND_SECONDARY_ALT": "#e64a19",
        "BACKGROUND_TERTIARY": "#ff7043",
        "BACKGROUND_ACCENT": "#ff6e40",
        "BACKGROUND_MOBILE_PRIMARY": "#d84315",
        "BACKGROUND_MOBILE_SECONDARY": "#d84315"
    },
    "rawColors": {
        "PRIMARY_100": "#ffccbc",
        "PRIMARY_130": "#ffab91",
        "PRIMARY_200": "#e57373",
        "PRIMARY_230": "#e57373",
        "PRIMARY_300": "#bcaaa4",
        "PRIMARY_360": "#bcaaa4",
        "PRIMARY_400": "#a1887f",
        "PRIMARY_460": "#8d6e63",
        "PRIMARY_500": "#794d40",
        "PRIMARY_560": "#5d4037",
        "PRIMARY_600": "#4e342e",
        "PRIMARY_630": "#3e2723",
        "PRIMARY_660": "#3e2723",
        "PRIMARY_700": "#3e2723",
        "PRIMARY_800": "#3e2723",
        "PLUM_1": "#ffeb3b",
        "PLUM_3": "#f50057",
        "PLUM_6": "#ff4081"
    },
    "plus": {
        "version": 0,
        "customOverlays": true,
        "icons": {
            "ic_mic_neutral": "#ffcc80"
        },
        "iconpack": "custom-icons"
    },
    "spec": 2
}
